takeme_mailgun/__init__.py
takeme_mailgun-1.0.8.dist-info/LICENSE
takeme_mailgun-1.0.8.dist-info/METADATA
takeme_mailgun-1.0.8.dist-info/WHEEL
takeme_mailgun-1.0.8.dist-info/top_level.txt
takeme_mailgun-1.0.8.dist-info/RECORD
