Metadata-Version: 2.1
Name: takeme-mailgun
Version: 1.0.8
Summary: Python Wrapper for Mailgun API
Home-page: https://github.com/takeme-pay/mailgun
Author: Yukitaka Maeda
Author-email: yukitaka.maeda@japanfoodie.jp
License: GPLv3+
Keywords: mailgun mail TakeMe
Platform: any
Classifier: Programming Language :: Python
Classifier: Programming Language :: Python :: 3
Requires-Dist: requests
